qdudomportal
